omniauto/__init__.py
omniauto/cli.py
omniauto/core.py
omniauto/decorators.py
omniauto/discovery.py
omniauto/generator.py
omniauto/utils.py
omniauto-0.1.1.dist-info/licenses/LICENSE
omniauto-0.1.1.dist-info/METADATA
omniauto-0.1.1.dist-info/WHEEL
omniauto-0.1.1.dist-info/top_level.txt
omniauto-0.1.1.dist-info/RECORD
