Metadata-Version: 2.4
Name: omniauto
Version: 0.1.1
Summary: Single Point of Truth dinámico para proyectos Python
Home-page: https://github.com/Dancenot0/omniauto
Author: Dancenot0
Author-email: Dancenot0 <dancenot02@gmail.com>
License: MIT
Project-URL: Homepage, https://github.com/Dancenot0/omniauto
Classifier: Development Status :: 3 - Alpha
Classifier: License :: OSI Approved :: MIT License
Classifier: Programming Language :: Python :: 3
Requires-Python: >=3.7
License-File: LICENSE
Dynamic: author
Dynamic: home-page
Dynamic: license-file
Dynamic: requires-python
